{
  "Object Type": "Basin",
  "Brief Description": "Basin engraved with scenes from Iranian legend as well as Mongol imperial symbols, Iran, 1300-20.",
  "Materials and Techniques": "Copper alloy (brass) basin engraved and originally inlaid with silver and gold",
  "Place": "Iran (made)",
  "Accession Number": "546-1905",
  "Rights Statement": "Image and metadata usage subject to V&A <a href=\"https://www.vam.ac.uk/info/va-websites-terms-conditions\">Terms and Conditions</a>",
  "Manifest": "https://iiif.vam.ac.uk/collections/O67418/manifest.json"
}